c4ipcam/__init__.py
c4ipcam/client.py
c4ipcam/server.py
c4ipcam-0.0.4.dist-info/METADATA
c4ipcam-0.0.4.dist-info/WHEEL
c4ipcam-0.0.4.dist-info/entry_points.txt
c4ipcam-0.0.4.dist-info/top_level.txt
c4ipcam-0.0.4.dist-info/RECORD
