Metadata-Version: 2.1
Name: c4ipcam
Version: 0.0.4
Summary: Simple IP camera streaming module with authentication and compression for OpenCV applications.
Home-page: https://github.com/rtcctc/c4ipcam
Author: 4edbark
Author-email: vangogprogprog@gmail.com
Project-URL: GitHub, https://github.com/rtcctc/c4ipcam
Project-URL: Bug Reports, https://github.com/rtcctc/c4ipcam/issues
Project-URL: Documentation, https://github.com/rtcctc/c4ipcam#readme
Keywords: opencv,ip camera,streaming,video,computer vision,authentication
Classifier: Programming Language :: Python :: 3.11
Classifier: License :: OSI Approved :: MIT License
Classifier: Operating System :: OS Independent
Classifier: Development Status :: 4 - Beta
Classifier: Intended Audience :: Developers
Classifier: Topic :: Multimedia :: Video :: Capture
Classifier: Topic :: Software Development :: Libraries :: Python Modules
Requires-Python: >=3.6
Requires-Dist: opencv-python>=4.11.0.86
Requires-Dist: numpy>=1.21.0
